{
  "meta": {
    "stableOrder": true,
    "enableUnifiedLockfile": false
  },
  "lockfileVersion": 3,
  "ATTENTION": "THIS IS AN AUTOGENERATED FILE. DO NOT EDIT THIS FILE DIRECTLY.",
  "specifiers": {
    "@abner/app_log@lib/applog-signed-1.0.0.har": "@abner/app_log@lib/applog-signed-1.0.0.har",
    "@abner/monitor@lib/monitor-signed-1.0.0.har": "@abner/monitor@lib/monitor-signed-1.0.0.har",
    "@abner/slider@lib/slider-signed-1.0.0.har": "@abner/slider@lib/slider-signed-1.0.0.har"
  },
  "packages": {
    "@abner/app_log@lib/applog-signed-1.0.0.har": {
      "name": "@abner/app_log",
      "version": "1.0.0",
      "resolved": "lib/applog-signed-1.0.0.har",
      "registryType": "local"
    },
    "@abner/monitor@lib/monitor-signed-1.0.0.har": {
      "name": "@abner/monitor",
      "version": "1.0.0",
      "resolved": "lib/monitor-signed-1.0.0.har",
      "registryType": "local"
    },
    "@abner/slider@lib/slider-signed-1.0.0.har": {
      "name": "@abner/slider",
      "version": "1.0.0",
      "resolved": "lib/slider-signed-1.0.0.har",
      "registryType": "local"
    }
  }
}